{
  "name": "AVORTEMENT1",
  "annotates": "AVORTEMENT1.wav",
  "sampleRate": 44100,
  "levels": [
        {
          "name": "bundle",
          "type": "ITEM",
          "items": [
              {
                    "id": 0,
                    "labels": [
                        {
                            "name": "bundle",
                            "value": "AVORTEMENT1"
                        },
                        {
                            "name": "source",
                            "value": "maus"
                        },
                        {
                            "name": "SAM",
                            "value": "44100"
                        },
                        {
                            "name": "MAO",
                            "value": "VERSION=5.1,v=0,SIGNAL=/var/lib/tomcat7/webapps/BASWebServices##2.24//data//2018.12.16_11.34.50_ABE8F8A32BF66E3D937BFD094533701E/AVORTEMENT1.wav,BPF=/tmp/11757_1544959883_G2PBPFOUT.par,OUT=/var/lib/tomcat7/webapps/BASWebServices##2.24//data//2018.12.16_11.34.50_ABE8F8A32BF66E3D937BFD094533701E/AVORTEMENT1_annot.json,OUTFORMAT=emuDB,LANGUAGE=ltz-LU,RULESET=default,MINPAUSLEN=5,INSORTTEXTGRID=true,INSKANTEXTGRID=true,USETRN=false,PRESEG=false,OUTSYMBOL=ipa,NOINITIALFINALSILENCE=false,WEIGHT=default,INSPROB=0.0,STARTWORD=0,ENDWORD=999999,MODUS=standard,RELAXMINDUR=false,INSYMBOL=sampa,"
                        }
                    ]
              }
          ]
        },
        {
          "name": "ORT",
          "type": "ITEM",
          "items": [
              {
                    "id": 1,
                    "labels": [
                        {
                            "name": "ORT",
                            "value": "Avortement"
                        },
                        {
                            "name": "KAN",
                            "value": "A v O R t @ m { n t"
                        }
                    ]
              },
              {
                    "id": 2,
                    "labels": [
                        {
                            "name": "ORT",
                            "value": "'Avortementen'"
                        },
                        {
                            "name": "KAN",
                            "value": "A v O R t @ m A:~ @ n"
                        }
                    ]
              }
          ]
        },
        {
          "name": "MAU",
          "type": "SEGMENT",
          "items": [
              {
                    "id": 3,
                    "sampleStart": 0,
                    "sampleDur": 7055,
                    "labels": [
                        {
                            "name": "MAU",
                            "value": "(...)"
                        }
                    ]
              },
              {
                    "id": 4,
                    "sampleStart": 7056,
                    "sampleDur": 6614,
                    "labels": [
                        {
                            "name": "MAU",
                            "value": "ɑ"
                        }
                    ]
              },
              {
                    "id": 5,
                    "sampleStart": 13671,
                    "sampleDur": 2645,
                    "labels": [
                        {
                            "name": "MAU",
                            "value": "v"
                        }
                    ]
              },
              {
                    "id": 6,
                    "sampleStart": 16317,
                    "sampleDur": 5291,
                    "labels": [
                        {
                            "name": "MAU",
                            "value": "ɔ"
                        }
                    ]
              },
              {
                    "id": 7,
                    "sampleStart": 21609,
                    "sampleDur": 3086,
                    "labels": [
                        {
                            "name": "MAU",
                            "value": "ʀ"
                        }
                    ]
              },
              {
                    "id": 8,
                    "sampleStart": 24696,
                    "sampleDur": 2645,
                    "labels": [
                        {
                            "name": "MAU",
                            "value": "t"
                        }
                    ]
              },
              {
                    "id": 9,
                    "sampleStart": 27342,
                    "sampleDur": 3086,
                    "labels": [
                        {
                            "name": "MAU",
                            "value": "ə"
                        }
                    ]
              },
              {
                    "id": 10,
                    "sampleStart": 30429,
                    "sampleDur": 3968,
                    "labels": [
                        {
                            "name": "MAU",
                            "value": "m"
                        }
                    ]
              },
              {
                    "id": 11,
                    "sampleStart": 34398,
                    "sampleDur": 5291,
                    "labels": [
                        {
                            "name": "MAU",
                            "value": "æ"
                        }
                    ]
              },
              {
                    "id": 12,
                    "sampleStart": 39690,
                    "sampleDur": 2204,
                    "labels": [
                        {
                            "name": "MAU",
                            "value": "n"
                        }
                    ]
              },
              {
                    "id": 13,
                    "sampleStart": 41895,
                    "sampleDur": 1322,
                    "labels": [
                        {
                            "name": "MAU",
                            "value": "t"
                        }
                    ]
              },
              {
                    "id": 14,
                    "sampleStart": 43218,
                    "sampleDur": 35279,
                    "labels": [
                        {
                            "name": "MAU",
                            "value": "(...)"
                        }
                    ]
              },
              {
                    "id": 15,
                    "sampleStart": 78498,
                    "sampleDur": 6173,
                    "labels": [
                        {
                            "name": "MAU",
                            "value": "ɑ"
                        }
                    ]
              },
              {
                    "id": 16,
                    "sampleStart": 84672,
                    "sampleDur": 2204,
                    "labels": [
                        {
                            "name": "MAU",
                            "value": "v"
                        }
                    ]
              },
              {
                    "id": 17,
                    "sampleStart": 86877,
                    "sampleDur": 3527,
                    "labels": [
                        {
                            "name": "MAU",
                            "value": "ɔ"
                        }
                    ]
              },
              {
                    "id": 18,
                    "sampleStart": 90405,
                    "sampleDur": 2645,
                    "labels": [
                        {
                            "name": "MAU",
                            "value": "ʀ"
                        }
                    ]
              },
              {
                    "id": 19,
                    "sampleStart": 93051,
                    "sampleDur": 3968,
                    "labels": [
                        {
                            "name": "MAU",
                            "value": "t"
                        }
                    ]
              },
              {
                    "id": 20,
                    "sampleStart": 97020,
                    "sampleDur": 2645,
                    "labels": [
                        {
                            "name": "MAU",
                            "value": "ə"
                        }
                    ]
              },
              {
                    "id": 21,
                    "sampleStart": 99666,
                    "sampleDur": 3086,
                    "labels": [
                        {
                            "name": "MAU",
                            "value": "m"
                        }
                    ]
              },
              {
                    "id": 22,
                    "sampleStart": 102753,
                    "sampleDur": 8819,
                    "labels": [
                        {
                            "name": "MAU",
                            "value": "ɑ̃ː"
                        }
                    ]
              },
              {
                    "id": 23,
                    "sampleStart": 111573,
                    "sampleDur": 4409,
                    "labels": [
                        {
                            "name": "MAU",
                            "value": "ə"
                        }
                    ]
              },
              {
                    "id": 24,
                    "sampleStart": 115983,
                    "sampleDur": 8819,
                    "labels": [
                        {
                            "name": "MAU",
                            "value": "n"
                        }
                    ]
              },
              {
                    "id": 25,
                    "sampleStart": 124803,
                    "sampleDur": 29546,
                    "labels": [
                        {
                            "name": "MAU",
                            "value": "(...)"
                        }
                    ]
              }
          ]
        }
    ],
    "links": [
        {
            "fromID": 0,
            "toID": 1
        },
        {
            "fromID": 0,
            "toID": 2
        }
,
        {
            "fromID": 0,
            "toID": 3
        },
        {
            "fromID": 1,
            "toID": 4
        },
        {
            "fromID": 1,
            "toID": 5
        },
        {
            "fromID": 1,
            "toID": 6
        },
        {
            "fromID": 1,
            "toID": 7
        },
        {
            "fromID": 1,
            "toID": 8
        },
        {
            "fromID": 1,
            "toID": 9
        },
        {
            "fromID": 1,
            "toID": 10
        },
        {
            "fromID": 1,
            "toID": 11
        },
        {
            "fromID": 1,
            "toID": 12
        },
        {
            "fromID": 1,
            "toID": 13
        },
        {
            "fromID": 0,
            "toID": 14
        },
        {
            "fromID": 2,
            "toID": 15
        },
        {
            "fromID": 2,
            "toID": 16
        },
        {
            "fromID": 2,
            "toID": 17
        },
        {
            "fromID": 2,
            "toID": 18
        },
        {
            "fromID": 2,
            "toID": 19
        },
        {
            "fromID": 2,
            "toID": 20
        },
        {
            "fromID": 2,
            "toID": 21
        },
        {
            "fromID": 2,
            "toID": 22
        },
        {
            "fromID": 2,
            "toID": 23
        },
        {
            "fromID": 2,
            "toID": 24
        },
        {
            "fromID": 0,
            "toID": 25
        }


    ]
}
